pyramid_addons/__init__.py
pyramid_addons/helpers.py
pyramid_addons/tests.py
pyramid_addons/validation.py
pyramid_addons-0.21.dist-info/DESCRIPTION.rst
pyramid_addons-0.21.dist-info/METADATA
pyramid_addons-0.21.dist-info/metadata.json
pyramid_addons-0.21.dist-info/RECORD
pyramid_addons-0.21.dist-info/top_level.txt
pyramid_addons-0.21.dist-info/WHEEL
