Metadata-Version: 2.0
Name: pyramid-addons
Version: 0.21
Summary: A package containing extra needed pyramid functionality including helper functions and form validators.
Home-page: https://github.com/bboe/pyramid_addons
Author: Bryce Boe
Author-email: bbzbryce@gmail.com
License: Simplified BSD License
Keywords: pyramid validation addons
Platform: UNKNOWN
Classifier: Environment :: Console
Classifier: Intended Audience :: Developers
Classifier: License :: OSI Approved :: BSD License
Classifier: Natural Language :: English
Classifier: Operating System :: OS Independent
Classifier: Programming Language :: Python :: 2.6
Classifier: Programming Language :: Python :: 2.7
Classifier: Programming Language :: Python :: 3.2
Classifier: Topic :: Utilities
Requires-Dist: pyramid (>=1.3)
